 [
      {
        "name": "Semi Automatic Washing Machine",
        "image": "https://p.rmjo.in/productSquare/z227w1xz-500x500.jpg",
        "price": "$469/mo",
        "deliveryTime": "3-5 days"
      },
      {
        "name": "Single Door Fridge (170 Litre)",
        "image": "https://p.rmjo.in/productSquare/ue88wnov-500x500.jpg",
        "price": "$659/mo",
        "deliveryTime": "3-5 days"
      },
      {
        "name": "Air Conditioner 1 Ton",
        "image": "https://p.rmjo.in/productSquare/l6xann5r-500x500.jpg",
        "price": "$1859/mo",
        "deliveryTime": "3-5 days"
      },
      {
        "name": "Induction Cooktop",
        "image": "https://p.rmjo.in/productSquare/xev0b5yi-500x500.jpg",
        "price": "$149/mo",
        "deliveryTime": "3-5 days"
      }
    ]
  